schedule_management/__init__.py
schedule_management/reminder.py
schedule_management/reminder_macos.py
schedule_management/report.py
schedule_management/utils.py
schedule_management-0.4.0.dist-info/licenses/LICENSE
schedule_management-0.4.0.dist-info/METADATA
schedule_management-0.4.0.dist-info/WHEEL
schedule_management-0.4.0.dist-info/entry_points.txt
schedule_management-0.4.0.dist-info/top_level.txt
schedule_management-0.4.0.dist-info/RECORD
