Metadata-Version: 2.4
Name: schedule-management
Version: 0.4.0
Summary: A TOML based scheduling tool
License-Expression: MIT
Requires-Python: >=3.12
License-File: LICENSE
Requires-Dist: matplotlib>=3.10.6
Requires-Dist: pytest>=8.4.2
Requires-Dist: rich>=14.2.0
Dynamic: license-file
